gopad/__init__.py
gopad/api/__init__.py
gopad/api/auth_api.py
gopad/api/group_api.py
gopad/api/profile_api.py
gopad/api/user_api.py
gopad/api_client.py
gopad/api_response.py
gopad/configuration.py
gopad/exceptions.py
gopad/models/__init__.py
gopad/models/auth_token.py
gopad/models/auth_verify.py
gopad/models/create_group_request.py
gopad/models/create_user_request.py
gopad/models/delete_group_from_user_request.py
gopad/models/delete_user_from_group_request.py
gopad/models/group.py
gopad/models/list_group_users200_response.py
gopad/models/list_groups200_response.py
gopad/models/list_providers200_response.py
gopad/models/list_user_groups200_response.py
gopad/models/list_users200_response.py
gopad/models/login_auth_request.py
gopad/models/notification.py
gopad/models/permit_group_user_request.py
gopad/models/permit_user_group_request.py
gopad/models/profile.py
gopad/models/provider.py
gopad/models/redirect_auth_request.py
gopad/models/update_profile_request.py
gopad/models/update_user_request.py
gopad/models/user.py
gopad/models/user_auth.py
gopad/models/user_group.py
gopad/models/validation.py
gopad/py.typed
gopad/rest.py
gopad-2.1.1.dist-info/METADATA
gopad-2.1.1.dist-info/WHEEL
gopad-2.1.1.dist-info/licenses/LICENSE
gopad-2.1.1.dist-info/RECORD
